{
    "fixtures": [
        {
            "id": 53,
            "code": 2128340,
            "team_h": 8,
            "team_h_score": null,
            "team_a": 6,
            "team_a_score": null,
            "event": 6,
            "finished": false,
            "minutes": 0,
            "provisional_start_time": false,
            "kickoff_time": "2020-10-24T14:00:00Z",
            "event_name": "Gameweek 6",
            "is_home": false,
            "difficulty": 2
        },
        {
            "id": 68,
            "code": 2128355,
            "team_h": 20,
            "team_h_score": null,
            "team_a": 6,
            "team_a_score": null,
            "event": 7,
            "finished": false,
            "minutes": 0,
            "provisional_start_time": false,
            "kickoff_time": "2020-10-30T20:00:00Z",
            "event_name": "Gameweek 7",
            "is_home": false,
            "difficulty": 3
        },
        {
            "id": 72,
            "code": 2128359,
            "team_h": 6,
            "team_h_score": null,
            "team_a": 10,
            "team_a_score": null,
            "event": 8,
            "finished": false,
            "minutes": 0,
            "provisional_start_time": false,
            "kickoff_time": "2020-11-07T15:00:00Z",
            "event_name": "Gameweek 8",
            "is_home": true,
            "difficulty": 2
        },
        {
            "id": 80,
            "code": 2128367,
            "team_h": 4,
            "team_h_score": null,
            "team_a": 6,
            "team_a_score": null,
            "event": 9,
            "finished": false,
            "minutes": 0,
            "provisional_start_time": false,
            "kickoff_time": "2020-11-21T15:00:00Z",
            "event_name": "Gameweek 9",
            "is_home": false,
            "difficulty": 2
        },
        {
            "id": 92,
            "code": 2128379,
            "team_h": 6,
            "team_h_score": null,
            "team_a": 14,
            "team_a_score": null,
            "event": 10,
            "finished": false,
            "minutes": 0,
            "provisional_start_time": false,
            "kickoff_time": "2020-11-28T15:00:00Z",
            "event_name": "Gameweek 10",
            "is_home": true,
            "difficulty": 2
        },
        {
            "id": 107,
            "code": 2128394,
            "team_h": 18,
            "team_h_score": null,
            "team_a": 6,
            "team_a_score": null,
            "event": 11,
            "finished": false,
            "minutes": 0,
            "provisional_start_time": false,
            "kickoff_time": "2020-12-05T15:00:00Z",
            "event_name": "Gameweek 11",
            "is_home": false,
            "difficulty": 2
        },
        {
            "id": 110,
            "code": 2128397,
            "team_h": 6,
            "team_h_score": null,
            "team_a": 17,
            "team_a_score": null,
            "event": 12,
            "finished": false,
            "minutes": 0,
            "provisional_start_time": false,
            "kickoff_time": "2020-12-12T15:00:00Z",
            "event_name": "Gameweek 12",
            "is_home": true,
            "difficulty": 4
        },
        {
            "id": 125,
            "code": 2128412,
            "team_h": 19,
            "team_h_score": null,
            "team_a": 6,
            "team_a_score": null,
            "event": 13,
            "finished": false,
            "minutes": 0,
            "provisional_start_time": false,
            "kickoff_time": "2020-12-15T19:45:00Z",
            "event_name": "Gameweek 13",
            "is_home": false,
            "difficulty": 3
        },
        {
            "id": 132,
            "code": 2128419,
            "team_h": 6,
            "team_h_score": null,
            "team_a": 11,
            "team_a_score": null,
            "event": 14,
            "finished": false,
            "minutes": 0,
            "provisional_start_time": false,
            "kickoff_time": "2020-12-19T15:00:00Z",
            "event_name": "Gameweek 14",
            "is_home": true,
            "difficulty": 4
        },
        {
            "id": 140,
            "code": 2128427,
            "team_h": 2,
            "team_h_score": null,
            "team_a": 6,
            "team_a_score": null,
            "event": 15,
            "finished": false,
            "minutes": 0,
            "provisional_start_time": false,
            "kickoff_time": "2020-12-26T15:00:00Z",
            "event_name": "Gameweek 15",
            "is_home": false,
            "difficulty": 3
        },
        {
            "id": 152,
            "code": 2128439,
            "team_h": 6,
            "team_h_score": null,
            "team_a": 9,
            "team_a_score": null,
            "event": 16,
            "finished": false,
            "minutes": 0,
            "provisional_start_time": false,
            "kickoff_time": "2020-12-28T15:00:00Z",
            "event_name": "Gameweek 16",
            "is_home": true,
            "difficulty": 3
        },
        {
            "id": 162,
            "code": 2128449,
            "team_h": 6,
            "team_h_score": null,
            "team_a": 15,
            "team_a_score": null,
            "event": 17,
            "finished": false,
            "minutes": 0,
            "provisional_start_time": false,
            "kickoff_time": "2021-01-02T15:00:00Z",
            "event_name": "Gameweek 17",
            "is_home": true,
            "difficulty": 3
        },
        {
            "id": 169,
            "code": 2128456,
            "team_h": 1,
            "team_h_score": null,
            "team_a": 6,
            "team_a_score": null,
            "event": 18,
            "finished": false,
            "minutes": 0,
            "provisional_start_time": false,
            "kickoff_time": "2021-01-12T19:45:00Z",
            "event_name": "Gameweek 18",
            "is_home": false,
            "difficulty": 4
        },
        {
            "id": 185,
            "code": 2128472,
            "team_h": 12,
            "team_h_score": null,
            "team_a": 6,
            "team_a_score": null,
            "event": 19,
            "finished": false,
            "minutes": 0,
            "provisional_start_time": false,
            "kickoff_time": "2021-01-16T15:00:00Z",
            "event_name": "Gameweek 19",
            "is_home": false,
            "difficulty": 5
        },
        {
            "id": 195,
            "code": 2128482,
            "team_h": 6,
            "team_h_score": null,
            "team_a": 19,
            "team_a_score": null,
            "event": 20,
            "finished": false,
            "minutes": 0,
            "provisional_start_time": false,
            "kickoff_time": "2021-01-27T20:00:00Z",
            "event_name": "Gameweek 20",
            "is_home": true,
            "difficulty": 3
        },
        {
            "id": 202,
            "code": 2128489,
            "team_h": 6,
            "team_h_score": null,
            "team_a": 20,
            "team_a_score": null,
            "event": 21,
            "finished": false,
            "minutes": 0,
            "provisional_start_time": false,
            "kickoff_time": "2021-01-30T15:00:00Z",
            "event_name": "Gameweek 21",
            "is_home": true,
            "difficulty": 3
        },
        {
            "id": 217,
            "code": 2128504,
            "team_h": 14,
            "team_h_score": null,
            "team_a": 6,
            "team_a_score": null,
            "event": 22,
            "finished": false,
            "minutes": 0,
            "provisional_start_time": false,
            "kickoff_time": "2021-02-03T19:45:00Z",
            "event_name": "Gameweek 22",
            "is_home": false,
            "difficulty": 3
        },
        {
            "id": 222,
            "code": 2128509,
            "team_h": 10,
            "team_h_score": null,
            "team_a": 6,
            "team_a_score": null,
            "event": 23,
            "finished": false,
            "minutes": 0,
            "provisional_start_time": false,
            "kickoff_time": "2021-02-06T15:00:00Z",
            "event_name": "Gameweek 23",
            "is_home": false,
            "difficulty": 3
        },
        {
            "id": 232,
            "code": 2128519,
            "team_h": 6,
            "team_h_score": null,
            "team_a": 4,
            "team_a_score": null,
            "event": 24,
            "finished": false,
            "minutes": 0,
            "provisional_start_time": false,
            "kickoff_time": "2021-02-13T15:00:00Z",
            "event_name": "Gameweek 24",
            "is_home": true,
            "difficulty": 2
        },
        {
            "id": 241,
            "code": 2128528,
            "team_h": 3,
            "team_h_score": null,
            "team_a": 6,
            "team_a_score": null,
            "event": 25,
            "finished": false,
            "minutes": 0,
            "provisional_start_time": false,
            "kickoff_time": "2021-02-20T15:00:00Z",
            "event_name": "Gameweek 25",
            "is_home": false,
            "difficulty": 3
        },
        {
            "id": 250,
            "code": 2128537,
            "team_h": 6,
            "team_h_score": null,
            "team_a": 8,
            "team_a_score": null,
            "event": 26,
            "finished": false,
            "minutes": 0,
            "provisional_start_time": false,
            "kickoff_time": "2021-02-27T15:00:00Z",
            "event_name": "Gameweek 26",
            "is_home": true,
            "difficulty": 2
        },
        {
            "id": 266,
            "code": 2128553,
            "team_h": 17,
            "team_h_score": null,
            "team_a": 6,
            "team_a_score": null,
            "event": 27,
            "finished": false,
            "minutes": 0,
            "provisional_start_time": false,
            "kickoff_time": "2021-03-06T15:00:00Z",
            "event_name": "Gameweek 27",
            "is_home": false,
            "difficulty": 4
        },
        {
            "id": 270,
            "code": 2128557,
            "team_h": 6,
            "team_h_score": null,
            "team_a": 18,
            "team_a_score": null,
            "event": 28,
            "finished": false,
            "minutes": 0,
            "provisional_start_time": false,
            "kickoff_time": "2021-03-13T15:00:00Z",
            "event_name": "Gameweek 28",
            "is_home": true,
            "difficulty": 2
        },
        {
            "id": 281,
            "code": 2128568,
            "team_h": 6,
            "team_h_score": null,
            "team_a": 13,
            "team_a_score": null,
            "event": 29,
            "finished": false,
            "minutes": 0,
            "provisional_start_time": false,
            "kickoff_time": "2021-03-20T15:00:00Z",
            "event_name": "Gameweek 29",
            "is_home": true,
            "difficulty": 4
        },
        {
            "id": 292,
            "code": 2128579,
            "team_h": 7,
            "team_h_score": null,
            "team_a": 6,
            "team_a_score": null,
            "event": 30,
            "finished": false,
            "minutes": 0,
            "provisional_start_time": false,
            "kickoff_time": "2021-04-03T14:00:00Z",
            "event_name": "Gameweek 30",
            "is_home": false,
            "difficulty": 3
        },
        {
            "id": 301,
            "code": 2128588,
            "team_h": 6,
            "team_h_score": null,
            "team_a": 5,
            "team_a_score": null,
            "event": 31,
            "finished": false,
            "minutes": 0,
            "provisional_start_time": false,
            "kickoff_time": "2021-04-10T14:00:00Z",
            "event_name": "Gameweek 31",
            "is_home": true,
            "difficulty": 4
        },
        {
            "id": 317,
            "code": 2128604,
            "team_h": 16,
            "team_h_score": null,
            "team_a": 6,
            "team_a_score": null,
            "event": 32,
            "finished": false,
            "minutes": 0,
            "provisional_start_time": false,
            "kickoff_time": "2021-04-17T14:00:00Z",
            "event_name": "Gameweek 32",
            "is_home": false,
            "difficulty": 3
        },
        {
            "id": 323,
            "code": 2128610,
            "team_h": 9,
            "team_h_score": null,
            "team_a": 6,
            "team_a_score": null,
            "event": 33,
            "finished": false,
            "minutes": 0,
            "provisional_start_time": false,
            "kickoff_time": "2021-04-24T14:00:00Z",
            "event_name": "Gameweek 33",
            "is_home": false,
            "difficulty": 4
        },
        {
            "id": 332,
            "code": 2128619,
            "team_h": 6,
            "team_h_score": null,
            "team_a": 12,
            "team_a_score": null,
            "event": 34,
            "finished": false,
            "minutes": 0,
            "provisional_start_time": false,
            "kickoff_time": "2021-05-01T14:00:00Z",
            "event_name": "Gameweek 34",
            "is_home": true,
            "difficulty": 4
        },
        {
            "id": 346,
            "code": 2128633,
            "team_h": 15,
            "team_h_score": null,
            "team_a": 6,
            "team_a_score": null,
            "event": 35,
            "finished": false,
            "minutes": 0,
            "provisional_start_time": false,
            "kickoff_time": "2021-05-08T14:00:00Z",
            "event_name": "Gameweek 35",
            "is_home": false,
            "difficulty": 3
        },
        {
            "id": 355,
            "code": 2128642,
            "team_h": 6,
            "team_h_score": null,
            "team_a": 2,
            "team_a_score": null,
            "event": 36,
            "finished": false,
            "minutes": 0,
            "provisional_start_time": false,
            "kickoff_time": "2021-05-12T19:00:00Z",
            "event_name": "Gameweek 36",
            "is_home": true,
            "difficulty": 3
        },
        {
            "id": 362,
            "code": 2128649,
            "team_h": 6,
            "team_h_score": null,
            "team_a": 1,
            "team_a_score": null,
            "event": 37,
            "finished": false,
            "minutes": 0,
            "provisional_start_time": false,
            "kickoff_time": "2021-05-15T14:00:00Z",
            "event_name": "Gameweek 37",
            "is_home": true,
            "difficulty": 4
        },
        {
            "id": 374,
            "code": 2128661,
            "team_h": 11,
            "team_h_score": null,
            "team_a": 6,
            "team_a_score": null,
            "event": 38,
            "finished": false,
            "minutes": 0,
            "provisional_start_time": false,
            "kickoff_time": "2021-05-23T15:00:00Z",
            "event_name": "Gameweek 38",
            "is_home": false,
            "difficulty": 5
        }
    ],
    "history": [
        {
            "element": 140,
            "fixture": 1,
            "opponent_team": 16,
            "total_points": 2,
            "was_home": true,
            "kickoff_time": "2020-09-12T14:00:00Z",
            "team_h_score": 1,
            "team_a_score": 0,
            "round": 1,
            "minutes": 90,
            "goals_scored": 0,
            "assists": 0,
            "clean_sheets": 1,
            "goals_conceded": 0,
            "own_goals": 0,
            "penalties_saved": 0,
            "penalties_missed": 0,
            "yellow_cards": 0,
            "red_cards": 0,
            "saves": 0,
            "bonus": 0,
            "bps": -7,
            "influence": "9.2",
            "creativity": "0.8",
            "threat": "19.0",
            "ict_index": "2.9",
            "value": 60,
            "transfers_balance": 0,
            "selected": 403544,
            "transfers_in": 0,
            "transfers_out": 0
        },
        {
            "element": 140,
            "fixture": 15,
            "opponent_team": 13,
            "total_points": 5,
            "was_home": false,
            "kickoff_time": "2020-09-19T16:30:00Z",
            "team_h_score": 1,
            "team_a_score": 3,
            "round": 2,
            "minutes": 80,
            "goals_scored": 0,
            "assists": 1,
            "clean_sheets": 0,
            "goals_conceded": 1,
            "own_goals": 0,
            "penalties_saved": 0,
            "penalties_missed": 0,
            "yellow_cards": 0,
            "red_cards": 0,
            "saves": 0,
            "bonus": 0,
            "bps": 13,
            "influence": "7.2",
            "creativity": "0.3",
            "threat": "41.0",
            "ict_index": "4.9",
            "value": 60,
            "transfers_balance": -58033,
            "selected": 366405,
            "transfers_in": 22747,
            "transfers_out": 80780
        },
        {
            "element": 140,
            "fixture": 21,
            "opponent_team": 7,
            "total_points": 2,
            "was_home": true,
            "kickoff_time": "2020-09-26T14:00:00Z",
            "team_h_score": 1,
            "team_a_score": 2,
            "round": 3,
            "minutes": 81,
            "goals_scored": 0,
            "assists": 0,
            "clean_sheets": 0,
            "goals_conceded": 2,
            "own_goals": 0,
            "penalties_saved": 0,
            "penalties_missed": 0,
            "yellow_cards": 0,
            "red_cards": 0,
            "saves": 0,
            "bonus": 0,
            "bps": 3,
            "influence": "6.0",
            "creativity": "2.2",
            "threat": "2.0",
            "ict_index": "1.0",
            "value": 59,
            "transfers_balance": -57984,
            "selected": 320684,
            "transfers_in": 23450,
            "transfers_out": 81434
        },
        {
            "element": 140,
            "fixture": 31,
            "opponent_team": 5,
            "total_points": 2,
            "was_home": false,
            "kickoff_time": "2020-10-03T11:30:00Z",
            "team_h_score": 4,
            "team_a_score": 0,
            "round": 4,
            "minutes": 90,
            "goals_scored": 0,
            "assists": 0,
            "clean_sheets": 0,
            "goals_conceded": 4,
            "own_goals": 0,
            "penalties_saved": 0,
            "penalties_missed": 0,
            "yellow_cards": 0,
            "red_cards": 0,
            "saves": 0,
            "bonus": 0,
            "bps": 5,
            "influence": "4.6",
            "creativity": "2.8",
            "threat": "8.0",
            "ict_index": "1.5",
            "value": 59,
            "transfers_balance": -58242,
            "selected": 268502,
            "transfers_in": 12219,
            "transfers_out": 70461
        },
        {
            "element": 140,
            "fixture": 40,
            "opponent_team": 3,
            "total_points": 0,
            "was_home": true,
            "kickoff_time": "2020-10-18T13:00:00Z",
            "team_h_score": 1,
            "team_a_score": 1,
            "round": 5,
            "minutes": 0,
            "goals_scored": 0,
            "assists": 0,
            "clean_sheets": 0,
            "goals_conceded": 0,
            "own_goals": 0,
            "penalties_saved": 0,
            "penalties_missed": 0,
            "yellow_cards": 0,
            "red_cards": 0,
            "saves": 0,
            "bonus": 0,
            "bps": 0,
            "influence": "0.0",
            "creativity": "0.0",
            "threat": "0.0",
            "ict_index": "0.0",
            "value": 58,
            "transfers_balance": -41370,
            "selected": 232254,
            "transfers_in": 13397,
            "transfers_out": 54767
        }
    ],
    "history_past": [
        {
            "season_name": "2015/16",
            "element_code": 80146,
            "start_cost": 60,
            "end_cost": 54,
            "total_points": 86,
            "minutes": 2349,
            "goals_scored": 7,
            "assists": 0,
            "clean_sheets": 4,
            "goals_conceded": 51,
            "own_goals": 0,
            "penalties_saved": 0,
            "penalties_missed": 0,
            "yellow_cards": 6,
            "red_cards": 1,
            "saves": 0,
            "bonus": 13,
            "bps": 329,
            "influence": "0.0",
            "creativity": "0.0",
            "threat": "0.0",
            "ict_index": "0.0"
        },
        {
            "season_name": "2016/17",
            "element_code": 80146,
            "start_cost": 50,
            "end_cost": 50,
            "total_points": 39,
            "minutes": 867,
            "goals_scored": 1,
            "assists": 4,
            "clean_sheets": 5,
            "goals_conceded": 7,
            "own_goals": 0,
            "penalties_saved": 0,
            "penalties_missed": 0,
            "yellow_cards": 1,
            "red_cards": 0,
            "saves": 0,
            "bonus": 2,
            "bps": 122,
            "influence": "141.0",
            "creativity": "122.5",
            "threat": "219.0",
            "ict_index": "47.9"
        },
        {
            "season_name": "2017/18",
            "element_code": 80146,
            "start_cost": 50,
            "end_cost": 54,
            "total_points": 108,
            "minutes": 2850,
            "goals_scored": 7,
            "assists": 2,
            "clean_sheets": 7,
            "goals_conceded": 49,
            "own_goals": 0,
            "penalties_saved": 0,
            "penalties_missed": 0,
            "yellow_cards": 2,
            "red_cards": 1,
            "saves": 0,
            "bonus": 12,
            "bps": 382,
            "influence": "562.2",
            "creativity": "350.4",
            "threat": "944.0",
            "ict_index": "185.8"
        },
        {
            "season_name": "2018/19",
            "element_code": 80146,
            "start_cost": 60,
            "end_cost": 57,
            "total_points": 46,
            "minutes": 1176,
            "goals_scored": 1,
            "assists": 3,
            "clean_sheets": 5,
            "goals_conceded": 13,
            "own_goals": 0,
            "penalties_saved": 0,
            "penalties_missed": 0,
            "yellow_cards": 3,
            "red_cards": 0,
            "saves": 0,
            "bonus": 2,
            "bps": 114,
            "influence": "140.2",
            "creativity": "207.3",
            "threat": "421.0",
            "ict_index": "76.7"
        },
        {
            "season_name": "2019/20",
            "element_code": 80146,
            "start_cost": 50,
            "end_cost": 51,
            "total_points": 132,
            "minutes": 3148,
            "goals_scored": 9,
            "assists": 3,
            "clean_sheets": 12,
            "goals_conceded": 45,
            "own_goals": 0,
            "penalties_saved": 0,
            "penalties_missed": 0,
            "yellow_cards": 6,
            "red_cards": 0,
            "saves": 0,
            "bonus": 19,
            "bps": 443,
            "influence": "597.4",
            "creativity": "445.6",
            "threat": "885.0",
            "ict_index": "192.4"
        }
    ]
}